hetznerdns/__init__.py
hetznerdns/api.py
hetznerdns/config.py
hetznerdns/exceptions.py
hetznerdns-1.0.6.data/scripts/hetznerdns-cli
hetznerdns-1.0.6.dist-info/LICENSE.txt
hetznerdns-1.0.6.dist-info/METADATA
hetznerdns-1.0.6.dist-info/WHEEL
hetznerdns-1.0.6.dist-info/top_level.txt
hetznerdns-1.0.6.dist-info/RECORD
