Metadata-Version: 2.1
Name: hetznerdns
Version: 1.0.6
Summary: An API and CLI client for Hetzner DNS service.
Home-page: UNKNOWN
Author: Ivan Ermilov
Author-email: ivan.s.ermilov@gmail.com
License: UNKNOWN
Platform: UNKNOWN
Classifier: Programming Language :: Python :: 3
Classifier: License :: OSI Approved :: MIT License
Classifier: Operating System :: OS Independent
Requires-Dist: click
Requires-Dist: requests
